grommunio_exporter/__debug__.py
grommunio_exporter/__init__.py
grommunio_exporter/__main__.py
grommunio_exporter/__version__.py
grommunio_exporter/configuration.py
grommunio_exporter/filetime.py
grommunio_exporter/grommunio_api.py
grommunio_exporter/metrics.py
grommunio_exporter/mysql_config.py
grommunio_exporter/path_helper.py
grommunio_exporter/server.py
grommunio_exporter-0.6.0.dist-info/LICENSE
grommunio_exporter-0.6.0.dist-info/METADATA
grommunio_exporter-0.6.0.dist-info/WHEEL
grommunio_exporter-0.6.0.dist-info/entry_points.txt
grommunio_exporter-0.6.0.dist-info/top_level.txt
grommunio_exporter-0.6.0.dist-info/RECORD
