Metadata-Version: 2.1
Name: grommunio_exporter
Version: 0.6.0
Summary: Grommunio email system data exporter for Prometheus
Home-page: https://github.com/netinvent/grommunio_exporter
Author: NetInvent - Orsiris de Jong
Author-email: contact@netinvent.fr
License: GPLv3
Keywords: mail,grommunio,prometheus,linux,cli,grafana
Classifier: Development Status :: 5 - Production/Stable
Classifier: Intended Audience :: End Users/Desktop
Classifier: Intended Audience :: System Administrators
Classifier: Intended Audience :: Information Technology
Classifier: Intended Audience :: Developers
Classifier: Intended Audience :: Science/Research
Classifier: Topic :: System :: Archiving :: Backup
Classifier: Topic :: System
Classifier: Topic :: System :: Monitoring
Classifier: Topic :: Utilities
Classifier: Programming Language :: Python
Classifier: Programming Language :: Python :: 3
Classifier: Programming Language :: Python :: 3.6
Classifier: Programming Language :: Python :: 3.7
Classifier: Programming Language :: Python :: 3.8
Classifier: Programming Language :: Python :: 3.9
Classifier: Programming Language :: Python :: 3.10
Classifier: Programming Language :: Python :: 3.11
Classifier: Programming Language :: Python :: Implementation :: CPython
Classifier: Programming Language :: Python :: Implementation :: PyPy
Classifier: Operating System :: POSIX :: Linux
Classifier: License :: OSI Approved :: GNU General Public License v3 (GPLv3)
Requires-Python: >=3.6
License-File: LICENSE
Requires-Dist: command-runner >=1.7.3
Requires-Dist: ruamel.yaml
Requires-Dist: ofunctions.logger-utils >=2.4.0
Requires-Dist: gunicorn
Requires-Dist: uvicorn[standard]
Requires-Dist: fastapi
Requires-Dist: fastapi-offline >=1.3.2
Requires-Dist: pydantic >=1.9.2
Requires-Dist: prometheus-client >=0.9.0
Requires-Dist: cryptidy >=1.2.2
Requires-Dist: ofunctions.misc >=1.8.0
Requires-Dist: mysql-connector-python
